{
	"configurations" : 
	[
		{
			"directories" : 
			[
				{
					"build" : ".",
					"jsonFile" : "directory-.-Debug-d0094a50bb2071803777.json",
					"minimumCMakeVersion" : 
					{
						"string" : "3.17"
					},
					"projectIndex" : 0,
					"source" : ".",
					"targetIndexes" : 
					[
						0
					]
				}
			],
			"name" : "Debug",
			"projects" : 
			[
				{
					"directoryIndexes" : 
					[
						0
					],
					"name" : "m04_textures",
					"targetIndexes" : 
					[
						0
					]
				}
			],
			"targets" : 
			[
				{
					"directoryIndex" : 0,
					"id" : "06-mixed-colors::@6890427a1f51a3e7e1df",
					"jsonFile" : "target-06-mixed-colors-Debug-ff958d0113c37b6343a6.json",
					"name" : "06-mixed-colors",
					"projectIndex" : 0
				}
			]
		}
	],
	"kind" : "codemodel",
	"paths" : 
	{
		"build" : "C:/Users/ke_ni/OneDrive/Documents/Freshman - Junior/CS 4722/assignment6 - mixcolors file - Nichols/m04-textures/cmake-build-debug",
		"source" : "C:/Users/ke_ni/OneDrive/Documents/Freshman - Junior/CS 4722/assignment6 - mixcolors file - Nichols/m04-textures"
	},
	"version" : 
	{
		"major" : 2,
		"minor" : 4
	}
}
